[{"groupId":"120363132562172546@g.us","comandos":[]},{"groupId":"557991370553-1633730858@g.us","comandos":[]},{"groupId":"120363055373936431@g.us","comandos":[]},{"groupId":"120363052183964470@g.us","comandos":[]},{"groupId":"120363043837942965@g.us","comandos":[]},{"groupId":"120363140227688385@g.us","comandos":[]},{"groupId":"120363161410094714@g.us","comandos":[]},{"groupId":"120363089111958709@g.us","comandos":[]},{"groupId":"994409567740-1621113533@g.us","comandos":[]},{"groupId":"120363156824186773@g.us","comandos":[]},{"groupId":"120363159309999963@g.us","comandos":[]},{"groupId":"120363046994840467@g.us","comandos":[]},{"groupId":"120363062382644352@g.us","comandos":[]},{"groupId":"120363155947776006@g.us","comandos":[]},{"groupId":"120363140683469943@g.us","comandos":[]},{"groupId":"120363050232048442@g.us","comandos":[]},{"groupId":"120363108656690946@g.us","comandos":[]},{"groupId":"120363140000206401@g.us","comandos":[]},{"groupId":"120363160997386346@g.us","comandos":[]},{"groupId":"5512996828125-1604274406@g.us","comandos":[]},{"groupId":"120363046548548503@g.us","comandos":[]},{"groupId":"120363158360461959@g.us","comandos":[]},{"groupId":"120363028858456410@g.us","comandos":[]},{"groupId":"120363029178735179@g.us","comandos":[]},{"groupId":"120363094244463491@g.us","comandos":[]},{"groupId":"120363140957864661@g.us","comandos":[]},{"groupId":"120363142434283856@g.us","comandos":[]},{"groupId":"120363024922797828@g.us","comandos":[]},{"groupId":"120363161726758322@g.us","comandos":[]},{"groupId":"120363162706624743@g.us","comandos":[]},{"groupId":"120363162812679805@g.us","comandos":[]},{"groupId":"120363143424130385@g.us","comandos":[]},{"groupId":"120363161000910181@g.us","comandos":[]},{"groupId":"120363146754006621@g.us","comandos":[]},{"groupId":"120363162257866981@g.us","comandos":[]},{"groupId":"120363163720080357@g.us","comandos":[]},{"groupId":"120363146795578372@g.us","comandos":[]},{"groupId":"120363144645348321@g.us","comandos":[]},{"groupId":"120363147309076759@g.us","comandos":[]},{"groupId":"120363163393048677@g.us","comandos":[]},{"groupId":"120363161562583443@g.us","comandos":[]},{"groupId":"120363165586899291@g.us","comandos":[]},{"groupId":"120363147660151839@g.us","comandos":[]},{"groupId":"120363146956993181@g.us","comandos":[]},{"groupId":"120363165967013187@g.us","comandos":[]},{"groupId":"120363146326529184@g.us","comandos":[]},{"groupId":"120363149625412260@g.us","comandos":[]},{"groupId":"120363167561127975@g.us","comandos":[]},{"groupId":"120363153608224669@g.us","comandos":[]},{"groupId":"120363163284246934@g.us","comandos":[]},{"groupId":"120363044678698424@g.us","comandos":[]},{"groupId":"120363142627371284@g.us","comandos":[]},{"groupId":"120363166962152632@g.us","comandos":[]},{"groupId":"120363143332800927@g.us","comandos":[]},{"groupId":"120363164415247063@g.us","comandos":[]},{"groupId":"120363161461717379@g.us","comandos":[]},{"groupId":"120363169326720673@g.us","comandos":[]},{"groupId":"120363046109225190@g.us","comandos":[]},{"groupId":"120363160142567532@g.us","comandos":[]},{"groupId":"120363163019350485@g.us","comandos":[]},{"groupId":"120363147803695259@g.us","comandos":[]},{"groupId":"120363150762310883@g.us","comandos":[]},{"groupId":"120363151134316487@g.us","comandos":[]},{"groupId":"120363171214428418@g.us","comandos":[]},{"groupId":"120363183148857344@g.us","comandos":[]},{"groupId":"120363162828747723@g.us","comandos":[]},{"groupId":"120363166322370638@g.us","comandos":["promover","rebaixar","play"]},{"groupId":"120363165852365001@g.us","comandos":[]},{"groupId":"120363153370793187@g.us","comandos":[]},{"groupId":"120363184105043112@g.us","comandos":[]},{"groupId":"120363177362056599@g.us","comandos":[]},{"groupId":"120363172967096431@g.us","comandos":[]},{"groupId":"120363197976579911@g.us","comandos":[]},{"groupId":"120363046107732897@g.us","comandos":[]},{"groupId":"120363182272559979@g.us","comandos":[]},{"groupId":"120363183733863896@g.us","comandos":[]},{"groupId":"120363198189774633@g.us","comandos":[]},{"groupId":"120363165752171431@g.us","comandos":[]},{"groupId":"120363056032276410@g.us","comandos":[]},{"groupId":"120363041776521183@g.us","comandos":[]},{"groupId":"120363161972729484@g.us","comandos":[]},{"groupId":"120363194655718131@g.us","comandos":[]},{"groupId":"120363212744663516@g.us","comandos":[]},{"groupId":"120363198496657805@g.us","comandos":[]},{"groupId":"120363213834980318@g.us","comandos":[]},{"groupId":"120363026833414324@g.us","comandos":[]},{"groupId":"120363191947582678@g.us","comandos":[]},{"groupId":"120363189770279392@g.us","comandos":[]},{"groupId":"120363215245514350@g.us","comandos":[]},{"groupId":"120363086529790122@g.us","comandos":[]},{"groupId":"120363191424525117@g.us","comandos":[]},{"groupId":"120363196095936975@g.us","comandos":[]},{"groupId":"120363183220044581@g.us","comandos":[]},{"groupId":"120363190956019060@g.us","comandos":[]},{"groupId":"120363192884083217@g.us","comandos":[]},{"groupId":"120363202951380368@g.us","comandos":[]},{"groupId":"120363178901758585@g.us","comandos":[]},{"groupId":"120363200682837094@g.us","comandos":[]},{"groupId":"120363230755780608@g.us","comandos":[]},{"groupId":"120363216508310242@g.us","comandos":[]},{"groupId":"120363155284677906@g.us","comandos":[]},{"groupId":"120363233716500577@g.us","comandos":[]},{"groupId":"120363234510055476@g.us","comandos":[]},{"groupId":"120363237331209336@g.us","comandos":[]},{"groupId":"120363223514964593@g.us","comandos":[]},{"groupId":"120363233458332533@g.us","comandos":[]},{"groupId":"120363222428408961@g.us","comandos":[]},{"groupId":"120363194849477188@g.us","comandos":[]},{"groupId":"120363219755282052@g.us","comandos":[]},{"groupId":"120363137911713850@g.us","comandos":[]},{"groupId":"120363257711341433@g.us","comandos":[]},{"groupId":"120363219628809376@g.us","comandos":[]},{"groupId":"558185012120-1566736977@g.us","comandos":[]},{"groupId":"120363171231484102@g.us","comandos":[]},{"groupId":"120363257534146909@g.us","comandos":[]},{"groupId":"120363176795920342@g.us","comandos":[]},{"groupId":"120363204166411287@g.us","comandos":[]},{"groupId":"120363186203868469@g.us","comandos":[]},{"groupId":"120363192756542244@g.us","comandos":[]}]